lapin/__init__.py
lapin/__main__.py
lapin/scheduler.py
lapin/configs/__init__.py
lapin/configs/database.py
lapin/configs/mtl_opendata.py
lapin/configs/others.py
lapin/configs/road_network.py
lapin/configs/tennery_creek.py
lapin/configs/user_conf.py
lapin/constants/__init__.py
lapin/constants/analyses.py
lapin/constants/enhancement.py
lapin/constants/geom.py
lapin/constants/io.py
lapin/constants/lpr_data.py
lapin/constants/mapmatch.py
lapin/constants/restrictions.py
lapin/constants/road_network.py
lapin/constants/timezone.py
lapin/core/__init__.py
lapin/core/_utils.py
lapin/core/geobase_network.py
lapin/core/lpr.py
lapin/core/restrictions.py
lapin/core/study.py
lapin/core/trajectory.py
lapin/figures/__init__.py
lapin/figures/base.py
lapin/figures/colors.py
lapin/figures/config.py
lapin/figures/folium.py
lapin/figures/occup.py
lapin/figures/prov.py
lapin/figures/reassignement.py
lapin/figures/rempla.py
lapin/io/__init__.py
lapin/io/azure_cosmos.py
lapin/io/load.py
lapin/io/s3.py
lapin/io/sql.py
lapin/io/sqlalchemy_utils.py
lapin/io/types.py
lapin/io/utils.py
lapin/models/__init__.py
lapin/models/basic.py
lapin/models/occup.py
lapin/models/prov.py
lapin/models/reassignement.py
lapin/models/rempla.py
lapin/models/utils.py
lapin/processing/__init__.py
lapin/processing/cluster.py
lapin/processing/enhancement.py
lapin/processing/filter.py
lapin/processing/lap.py
lapin/processing/mapmatch.py
lapin/processing/matcher.py
lapin/processing/provenance.py
lapin/processing/road_network.py
lapin/processing/utils.py
lapin/tools/__init__.py
lapin/tools/ctime.py
lapin/tools/curbsnapp.py
lapin/tools/geom.py
lapin/tools/graph.py
lapin/tools/strings.py
lapin/tools/utils.py
lapin/transactions/__init__.py
lapin/transactions/connections.py
lapin/transactions/constants.py
lapin/transactions/core.py
lapin/transactions/querry.py
lapin/transactions/sql_permits.py
lapin/transactions/sql_places.py
lapin/transactions/sql_regulations.py
lapin/transactions/sql_transactions.py
onstreet_parking_study-1.2.10.dist-info/licenses/LICENSE
onstreet_parking_study-1.2.10.dist-info/METADATA
onstreet_parking_study-1.2.10.dist-info/WHEEL
onstreet_parking_study-1.2.10.dist-info/top_level.txt
onstreet_parking_study-1.2.10.dist-info/RECORD
